grammardetector/Cache.py
grammardetector/Config.py
grammardetector/GrammarDetector.py
grammardetector/Input.py
grammardetector/Nlp.py
grammardetector/Repository.py
grammardetector/__init__.py
grammardetector/__main__.py
grammardetector/defaults.py
grammardetector/logger.py
grammardetector/detectors/Detector.py
grammardetector/detectors/DetectorRepository.py
grammardetector/detectors/DetectorTester.py
grammardetector/detectors/__init__.py
grammardetector/loaders/FileLoader.py
grammardetector/loaders/YamlLoader.py
grammardetector/loaders/__init__.py
grammardetector/matchers/MatchSetMatcher.py
grammardetector/matchers/PatternSetMatcher.py
grammardetector/matchers/RawMatcher.py
grammardetector/matchers/__init__.py
grammardetector/matches/Match.py
grammardetector/matches/MatchSet.py
grammardetector/matches/__init__.py
grammardetector/patterns/Pattern.py
grammardetector/patterns/PatternSet.py
grammardetector/patterns/PatternSetRepository.py
grammardetector/patterns/__init__.py
grammardetector/utils/Filepath.py
grammardetector/utils/__init__.py
grammardetector/utils/flatten.py
grammardetector/utils/singleton.py
grammardetector/utils/token_data.py
grammardetector/utils/token_table.py
patternsets/__init__.py
patternsets/determiners.yaml
patternsets/persons.yaml
patternsets/tense_aspects.yaml
patternsets/transitivity.yaml
patternsets/voices.yaml
grammar_detector-0.2.4.dist-info/LICENSE.txt
grammar_detector-0.2.4.dist-info/METADATA
grammar_detector-0.2.4.dist-info/WHEEL
grammar_detector-0.2.4.dist-info/top_level.txt
grammar_detector-0.2.4.dist-info/RECORD
