Metadata-Version: 2.1
Name: grammar-detector
Version: 0.2.4
Summary: A grammatical feature detector for analyzing sentences, clauses, and phrases.
Author: Kyle Crawford
License: GNU GENERAL PUBLIC LICENSE
Project-URL: Homepage, https://github.com/SKCrawford/grammar-detector
Project-URL: Bug Tracker, https://github.com/SKCrawford/grammar-detector/issues
Requires-Python: >=3.9
License-File: LICENSE.txt
Requires-Dist: importlib-metadata
Requires-Dist: pyyaml
Requires-Dist: spacy
Requires-Dist: spacy-lookups-data
Requires-Dist: tabulate
Provides-Extra: dev
Requires-Dist: black ; extra == 'dev'
Requires-Dist: mypy ; extra == 'dev'
Requires-Dist: python-lsp-server ; extra == 'dev'
Requires-Dist: types-pyyaml ; extra == 'dev'
Requires-Dist: types-tabulate ; extra == 'dev'
Requires-Dist: types-setuptools ; extra == 'dev'
